pysample/__init__.py
pysample/client.py
pysample/command_line.py
pysample/context.py
pysample/repository.py
pysample/sampler.py
pysample/timer.py
pysample/transport.py
pysample/_cython/sample.cpython-37m-darwin.so
pysample/contrib/__init__.py
pysample/contrib/flask.py
server/__init__.py
server/app.py
tests/__init__.py
tests/test_client.py
tests/test_context.py
tests/test_memory_leak.py
tests/test_sampler.py
tests/test_server.py
tests/scripts/__init__.py
tests/scripts/busy_loop.py
tests/scripts/http_request.py
pysample_profiler-1.0.3.dist-info/LICENSE.md
pysample_profiler-1.0.3.dist-info/METADATA
pysample_profiler-1.0.3.dist-info/WHEEL
pysample_profiler-1.0.3.dist-info/entry_points.txt
pysample_profiler-1.0.3.dist-info/top_level.txt
pysample_profiler-1.0.3.dist-info/RECORD
