Metadata-Version: 2.1
Name: pysample-profiler
Version: 1.0.3
Summary: Sampling profiler for Python programs
Home-page: https://github.com/James-xie/pysample
Author: James Xie
Author-email: yanyin0703@163.com
License: MIT
Platform: UNKNOWN
